gitlab/__init__.py
gitlab/crud.py
gitlab/endpoints.py
gitlab/py.typed
gitlab/resources.py
gitlab/rpcs.py
gitlab/typing.py
gitlab/utils.py
gitlab_cli/__init__.py
gitlab_cli/ci_utils.py
gitlab_cli/data.py
gitlab_cli/get.py
python_gitlab_api-0.2.32.dist-info/entry_points.txt
python_gitlab_api-0.2.32.dist-info/LICENSE
python_gitlab_api-0.2.32.dist-info/WHEEL
python_gitlab_api-0.2.32.dist-info/METADATA
python_gitlab_api-0.2.32.dist-info/RECORD
