Metadata-Version: 2.1
Name: python-gitlab-api
Version: 0.2.32
Summary: Programmatic REST Client for GitLab
Home-page: https://gitlab.com/labs.kalfa.dev/python-gitlab-api/
License: LGPL-3.0-or-later
Author: Cosimo Alfarano
Author-email: cosimo@alfarano.net
Requires-Python: >=3.7,<4.0
Classifier: License :: OSI Approved :: GNU Lesser General Public License v3 or later (LGPLv3+)
Classifier: Programming Language :: Python :: 3
Classifier: Programming Language :: Python :: 3.10
Classifier: Programming Language :: Python :: 3.7
Classifier: Programming Language :: Python :: 3.8
Classifier: Programming Language :: Python :: 3.9
Requires-Dist: Jinja2 (>=2.11.3,<3.0.0)
Requires-Dist: PyYAML (>=5.4.1,<6.0.0)
Requires-Dist: click (>=7.1.2,<8.0.0)
Requires-Dist: dataclasses (>=0.8,<0.9); python_version >= "3.6" and python_version < "3.7"
Requires-Dist: jsonpath-ng (>=1.5.2,<2.0.0)
Requires-Dist: packaging (>=20.9,<21.0)
Requires-Dist: requests (>=2.25.1,<3.0.0)
Requires-Dist: url-normalize (>=1.4.3,<2.0.0)
Project-URL: Repository, https://gitlab.com/labs.kalfa.dev/python-gitlab-api/
